NetHyTech_MCV/__init__.py
NetHyTech_MCV-1.1.dist-info/METADATA
NetHyTech_MCV-1.1.dist-info/WHEEL
NetHyTech_MCV-1.1.dist-info/top_level.txt
NetHyTech_MCV-1.1.dist-info/RECORD
